simple_socket/__init__.py
simple_socket/tcp_client.py
simple_socket/tcp_server.py
simple_socket/udp_client.py
simple_socket-0.0.10.dist-info/METADATA
simple_socket-0.0.10.dist-info/WHEEL
simple_socket-0.0.10.dist-info/top_level.txt
simple_socket-0.0.10.dist-info/RECORD
