Metadata-Version: 2.1
Name: simple-socket
Version: 0.0.10
Summary: Simple event-based socket objects
Home-page: https://github.com/GrantGMiller/simple_socket
Author: Grant Miller
Author-email: grant@grant-miller.com
License: MIT
Platform: UNKNOWN
